mlauto/__init__.py
mlauto/mlauto.py
tunerml-0.1.0.dist-info/METADATA
tunerml-0.1.0.dist-info/WHEEL
tunerml-0.1.0.dist-info/top_level.txt
tunerml-0.1.0.dist-info/RECORD
