Metadata-Version: 2.1
Name: tunerml
Version: 0.1.0
Summary: UNKNOWN
Home-page: https://github.com/ansariminhaj/mlauto_pip
Author: Minhaj Ansari
License: MIT
Platform: UNKNOWN
Classifier: Intended Audience :: Science/Research
Classifier: Programming Language :: Python :: 3
Requires-Dist: numpy
